crewplus_client/__init__.py
crewplus_client/client.py
crewplus_client/exceptions.py
crewplus_client/managers/__init__.py
crewplus_client/managers/ingestion.py
crewplus_client/managers/knowledge_base.py
crewplus_client/managers/task.py
crewplus_client/models/__init__.py
crewplus_client/models/ingestion.py
crewplus_client/models/knowledge_base.py
crewplus_client/models/task.py
crewplus_python-0.1.4.dist-info/METADATA
crewplus_python-0.1.4.dist-info/WHEEL
crewplus_python-0.1.4.dist-info/RECORD
