Metadata-Version: 2.3
Name: crewplus-python
Version: 0.1.4
Summary: The official Python SDK for Crewplus, used to interact with Crewplus backend services programmatically.
License: MIT
Keywords: crewplus,sdk,opsmateai,agent
Author: OpsmateAI
Author-email: contact@opsmate.ai
Requires-Python: >=3.12,<3.13
Classifier: License :: OSI Approved :: MIT License
Classifier: Programming Language :: Python :: 3
Classifier: Programming Language :: Python :: 3.12
Requires-Dist: pydantic (>=2.5.0,<3.0.0)
Requires-Dist: requests (>=2.31.0,<3.0.0)
Project-URL: Homepage, https://www.opsmate.ai/
Project-URL: Repository, https://github.com/opsmate/crewplus-platform
